{"article": ["brushing your teeth is one of the most elementary aspects of good hygiene ."], "abstract": ["brushing teeth is only half the game"], "candidates": [[["brushing your teeth is one of the most elementary aspects of good hygiene."], 0.3037037037037037], [["brushing your teeth is one of the most elementary aspects of good hygiene."], 0.3037037037037037], [["brushing your teeth is one of the most elementary aspects of good hygiene."], 0.3037037037037037], [["brushing teeth is one of the most elementary aspects of good hygiene."], 0.3591331269349845], [["brushing your teeth is one of the most elementary aspects of good hygiene."], 0.3037037037037037], [["brushing your teeth is one of the most elementary aspects of good hygiene."], 0.3037037037037037], [["brush is one of the most elementary aspects of good hygiene."], 0.22222222222222218], [["brushing teeth is one of the most elementary aspects of good hygiene."], 0.3591331269349845], [["brushes your teeth.", "it's one of the most elementary aspects of good hygiene."], 0.19047619047619047], [["brushing your teeth is one of the most elementary aspects of good hygiene."], 0.3037037037037037], [["brushing your teeth is one of the most elementary aspects of good hygiene."], 0.3037037037037037], [["brush your teeth: the essential hygiene tip."], 0.2857142857142857], [["brush your teeth is one of the most elementary parts of good hygiene."], 0.3037037037037037], [["the importance of brushing your teeth."], 0.2564102564102564], [["brushes your teeth is one of the most elementary aspects of good hygiene ."], 0.3037037037037037], [["the most basic hygiene tips."], 0.1111111111111111]], "article_untok": ["brushing your teeth is one of the most elementary aspects of good hygiene ."], "abstract_untok": ["brushing teeth is only half the game"], "candidates_untok": [[["brushing your teeth is one of the most elementary aspects of good hygiene."], 0.3037037037037037], [["brushing your teeth is one of the most elementary aspects of good hygiene."], 0.3037037037037037], [["brushing your teeth is one of the most elementary aspects of good hygiene."], 0.3037037037037037], [["brushing teeth is one of the most elementary aspects of good hygiene."], 0.3591331269349845], [["brushing your teeth is one of the most elementary aspects of good hygiene."], 0.3037037037037037], [["brushing your teeth is one of the most elementary aspects of good hygiene."], 0.3037037037037037], [["brush is one of the most elementary aspects of good hygiene."], 0.22222222222222218], [["brushing teeth is one of the most elementary aspects of good hygiene."], 0.3591331269349845], [["brushes your teeth.", "it's one of the most elementary aspects of good hygiene."], 0.19047619047619047], [["brushing your teeth is one of the most elementary aspects of good hygiene."], 0.3037037037037037], [["brushing your teeth is one of the most elementary aspects of good hygiene."], 0.3037037037037037], [["brush your teeth: the essential hygiene tip."], 0.2857142857142857], [["brush your teeth is one of the most elementary parts of good hygiene."], 0.3037037037037037], [["the importance of brushing your teeth."], 0.2564102564102564], [["brushes your teeth is one of the most elementary aspects of good hygiene ."], 0.3037037037037037], [["the most basic hygiene tips."], 0.1111111111111111]]}