{"article": ["india has offered to supply sri lanka 's oil requirements in the event of any disruption caused by a war in iraq , a senior government minister said thursday ."], "abstract": ["sri lanka banks on indian oil in case of war in iraq"], "candidates": [[["india has offered to supply sri lanka 's oil requirements in the event of any disruption caused by a war in iraq."], 0.3762254901960784], [["india offers to supply sri lanka 's oil requirements in the event of any disruption caused by a war in iraq."], 0.3877484522645813], [["to supply sri lanka 's oil requirements in the event of any disruption caused by a war in iraq."], 0.4130515387467557], [["india has offered to supply sri lanka 's oil requirements."], 0.21515151515151512], [["'s oil requirements in the event of any disruption caused by a war in iraq."], 0.3496296296296297], [["india has offered to supply sri lanka 's oil requirements in the event of any disruption caused by a war in iraq."], 0.3762254901960784], [["sri lanka has offered to supply oil in event of any disruption caused by a war in iraq."], 0.4507936507936508], [["india offered to supply sri lanka's oil in event of any disruption caused by a war in iraq."], 0.4360400444938821], [["india offers to supply sri lanka's oil in event of any disruption caused by a war in iraq."], 0.4360400444938821], [["oil requirements in the event of any disruption caused by a war in iraq."], 0.36324786324786323], [["sri lanka will be affected by a war in iraq, a senior government minister said."], 0.3269135802469136], [["india has offered to supply sri lanka 's oil requirements.", "in the event of any disruption caused by a war in iraq."], 0.3762254901960784], [["indian government minister says it will supply sri lanka with oil if there is a war in iraq."], 0.3603174603174603], [["ind india offers to supply sri lanka with oil if war in iraq disrupts oil supplies."], 0.3626373626373626], [["to supply oil in event of any disruption caused by war in iraq."], 0.40695652173913044], [["india has offered to supply sri lanka 's oil requirements."], 0.21515151515151512]], "article_untok": ["india has offered to supply sri lanka 's oil requirements in the event of any disruption caused by a war in iraq , a senior government minister said thursday ."], "abstract_untok": ["sri lanka banks on indian oil in case of war in iraq"], "candidates_untok": [[["india has offered to supply sri lanka 's oil requirements in the event of any disruption caused by a war in iraq."], 0.3762254901960784], [["india offers to supply sri lanka 's oil requirements in the event of any disruption caused by a war in iraq."], 0.3877484522645813], [["to supply sri lanka 's oil requirements in the event of any disruption caused by a war in iraq."], 0.4130515387467557], [["india has offered to supply sri lanka 's oil requirements."], 0.21515151515151512], [["'s oil requirements in the event of any disruption caused by a war in iraq."], 0.3496296296296297], [["india has offered to supply sri lanka 's oil requirements in the event of any disruption caused by a war in iraq."], 0.3762254901960784], [["sri lanka has offered to supply oil in event of any disruption caused by a war in iraq."], 0.4507936507936508], [["india offered to supply sri lanka's oil in event of any disruption caused by a war in iraq."], 0.4360400444938821], [["india offers to supply sri lanka's oil in event of any disruption caused by a war in iraq."], 0.4360400444938821], [["oil requirements in the event of any disruption caused by a war in iraq."], 0.36324786324786323], [["sri lanka will be affected by a war in iraq, a senior government minister said."], 0.3269135802469136], [["india has offered to supply sri lanka 's oil requirements.", "in the event of any disruption caused by a war in iraq."], 0.3762254901960784], [["indian government minister says it will supply sri lanka with oil if there is a war in iraq."], 0.3603174603174603], [["ind india offers to supply sri lanka with oil if war in iraq disrupts oil supplies."], 0.3626373626373626], [["to supply oil in event of any disruption caused by war in iraq."], 0.40695652173913044], [["india has offered to supply sri lanka 's oil requirements."], 0.21515151515151512]]}