{"article": ["police detained ## pakistani illegal immigrants hidden in a truck and arrested four smuggling suspects , including the greek driver , police said monday ."], "abstract": ["police detain ## illegal immigrants headed for italy"], "candidates": [[["police detained pakistani illegal immigrants hidden in a truck and arrested four smuggling suspects."], 0.3241436925647452], [["four smuggling suspects arrested, including the greek driver.", "police detained pakistani illegal immigrants hidden in a truck."], 0.2828282828282828], [["police detained pakistani illegal immigrants hidden in a truck and arrested four smuggling suspects."], 0.3241436925647452], [["police detained pakistani illegal immigrants hidden in a truck.", "four smuggling suspects were arrested, including the greek driver."], 0.271304347826087], [["police detained ## pakistani illegal immigrants hidden in a truck.", "four smuggling suspects were arrested, including the greek driver."], 0.271304347826087], [["pakistani illegal immigrants hidden in a truck and arrested four smuggling suspects, including the greek driver."], 0.14768806073153898], [["police detained four illegal immigrants hidden in a truck and arrested four smuggling suspects.", "police detained four smuggling suspect , including the greek driver."], 0.2253968253968254], [["four smuggling suspects, including the greek driver, were arrested, police said monday."], 0.07017543859649124], [["police detained a truck full of pakistani illegal immigrants hidden in a truck and arrested four smuggling suspects."], 0.271304347826087], [["four smuggling suspects arrested, including the greek driver."], 0.0], [["police detained four illegal immigrants hidden in a truck and arrested four smuggling suspects."], 0.3241436925647452], [["the four smuggling suspects were arrested, including the greek driver."], 0.0], [["police detained pakistani illegal immigrants hidden in a truck and arrested four smuggling suspects."], 0.3241436925647452], [["police arrested four smuggling suspects, including the greek driver."], 0.08333333333333333], [["police detain pakistani illegal immigrants hidden in a truck and arrest four smuggling suspects."], 0.3241436925647452], [["police detain pakistani illegal immigrants hidden in truck and arrest four smuggling suspects."], 0.34074074074074073]], "article_untok": ["police detained ## pakistani illegal immigrants hidden in a truck and arrested four smuggling suspects , including the greek driver , police said monday ."], "abstract_untok": ["police detain ## illegal immigrants headed for italy"], "candidates_untok": [[["police detained pakistani illegal immigrants hidden in a truck and arrested four smuggling suspects."], 0.3241436925647452], [["four smuggling suspects arrested, including the greek driver.", "police detained pakistani illegal immigrants hidden in a truck."], 0.2828282828282828], [["police detained pakistani illegal immigrants hidden in a truck and arrested four smuggling suspects."], 0.3241436925647452], [["police detained pakistani illegal immigrants hidden in a truck.", "four smuggling suspects were arrested, including the greek driver."], 0.271304347826087], [["police detained ## pakistani illegal immigrants hidden in a truck.", "four smuggling suspects were arrested, including the greek driver."], 0.271304347826087], [["pakistani illegal immigrants hidden in a truck and arrested four smuggling suspects, including the greek driver."], 0.14768806073153898], [["police detained four illegal immigrants hidden in a truck and arrested four smuggling suspects.", "police detained four smuggling suspect , including the greek driver."], 0.2253968253968254], [["four smuggling suspects, including the greek driver, were arrested, police said monday."], 0.07017543859649124], [["police detained a truck full of pakistani illegal immigrants hidden in a truck and arrested four smuggling suspects."], 0.271304347826087], [["four smuggling suspects arrested, including the greek driver."], 0.0], [["police detained four illegal immigrants hidden in a truck and arrested four smuggling suspects."], 0.3241436925647452], [["the four smuggling suspects were arrested, including the greek driver."], 0.0], [["police detained pakistani illegal immigrants hidden in a truck and arrested four smuggling suspects."], 0.3241436925647452], [["police arrested four smuggling suspects, including the greek driver."], 0.08333333333333333], [["police detain pakistani illegal immigrants hidden in a truck and arrest four smuggling suspects."], 0.3241436925647452], [["police detain pakistani illegal immigrants hidden in truck and arrest four smuggling suspects."], 0.34074074074074073]]}