{"article": ["in an effort to defuse nationwide protests , the indonesian government on monday agreed to sharply roll back a recent price hike on fuel ."], "abstract": ["indonesian government slashes controversial price hikes"], "candidates": [[["indonesian government agrees to sharply roll back a recent price hike on fuel."], 0.3591331269349845], [["government agrees to sharply roll back a recent price hike on fuel.", "in an effort to defuse nationwide protests."], 0.18898550724637678], [["the indonesian government agreed to sharply roll back a recent price hike on fuel."], 0.34074074074074073], [["indonesian government agrees to sharply roll back a recent price hike on fuel.", "price hike sparked nationwide protests."], 0.2828282828282828], [["indonesian government agrees to sharply roll back a recent price hike on fuel."], 0.3591331269349845], [["indonesian government agrees to sharply roll back a recent price hike on fuel."], 0.3591331269349845], [["the indonesian government on monday agreed to sharply roll back a recent price hike on fuel."], 0.30909090909090914], [["government agrees to sharply roll back a recent price hike on fuel."], 0.2638888888888889], [["indonesia agrees to sharply roll back a recent price hike on fuel.", "government hopes to defuse nationwide protests."], 0.19696969696969693], [["in an effort to defuse nationwide protests, indonesia agreed to sharply roll back a recent price hike on fuel."], 0.1356521739130435], [["the indonesian government has agreed to sharply roll back a recent price hike on fuel."], 0.3241436925647451], [["the indonesian government has agreed to sharply roll back a recent price hike on fuel."], 0.3241436925647451], [["indonesia agrees to sharply roll back a recent price hike on fuel."], 0.1898148148148148], [["indonesia agrees to sharply roll back a recent price hike on fuel.", "price hike sparked nationwide protests."], 0.14768806073153898], [["indonesian government agrees to sharply roll back price hike on fuel."], 0.4026143790849674], [["indonesia agrees to sharply roll back a recent price hike on fuel."], 0.1898148148148148]], "article_untok": ["in an effort to defuse nationwide protests , the indonesian government on monday agreed to sharply roll back a recent price hike on fuel ."], "abstract_untok": ["indonesian government slashes controversial price hikes"], "candidates_untok": [[["indonesian government agrees to sharply roll back a recent price hike on fuel."], 0.3591331269349845], [["government agrees to sharply roll back a recent price hike on fuel.", "in an effort to defuse nationwide protests."], 0.18898550724637678], [["the indonesian government agreed to sharply roll back a recent price hike on fuel."], 0.34074074074074073], [["indonesian government agrees to sharply roll back a recent price hike on fuel.", "price hike sparked nationwide protests."], 0.2828282828282828], [["indonesian government agrees to sharply roll back a recent price hike on fuel."], 0.3591331269349845], [["indonesian government agrees to sharply roll back a recent price hike on fuel."], 0.3591331269349845], [["the indonesian government on monday agreed to sharply roll back a recent price hike on fuel."], 0.30909090909090914], [["government agrees to sharply roll back a recent price hike on fuel."], 0.2638888888888889], [["indonesia agrees to sharply roll back a recent price hike on fuel.", "government hopes to defuse nationwide protests."], 0.19696969696969693], [["in an effort to defuse nationwide protests, indonesia agreed to sharply roll back a recent price hike on fuel."], 0.1356521739130435], [["the indonesian government has agreed to sharply roll back a recent price hike on fuel."], 0.3241436925647451], [["the indonesian government has agreed to sharply roll back a recent price hike on fuel."], 0.3241436925647451], [["indonesia agrees to sharply roll back a recent price hike on fuel."], 0.1898148148148148], [["indonesia agrees to sharply roll back a recent price hike on fuel.", "price hike sparked nationwide protests."], 0.14768806073153898], [["indonesian government agrees to sharply roll back price hike on fuel."], 0.4026143790849674], [["indonesia agrees to sharply roll back a recent price hike on fuel."], 0.1898148148148148]]}