{"article": ["grand champion asashoryu showed no sign on letting up friday when he overwhelmed tosanoumi to remain undefeated and tied for the lead with tamanoshima at the spring grand sumo tournament ."], "abstract": ["asashoryu marches on at spring sumo"], "candidates": [[["asashoryu remains undefeated and tied for the lead with tamanoshima at the spring grand sumo tournament."], 0.24242424242424243], [["asashoryu remains undefeated in spring grand sumo tournament.", "grand champion tamanoshima tied for the lead with tamanosima."], 0.17391304347826086], [["grand champion asashoryu remains undefeated in spring grand sumo tournament.", "asashorya is tied for the lead with tamanoshima."], 0.16666666666666666], [["grand champion asashoryu remains undefeated in spring grand sumo tournament.", "asashoryus remains undefeated and tied for the lead with tamanoshima."], 0.15384615384615383], [["grand champion remains undefeated in spring grand sumo tournament.", "asashoryu remains tied for the lead with tamanoshima."], 0.17391304347826086], [["grand sumo champion asashoryu remains undefeated.", "he is tied for the lead with tamanoshima."], 0.10000000000000002], [["asashoryu is still undefeated in the spring grand sumo tournament.", "he is tied with tamanoshima for the lead in the tournament."], 0.14814814814814817], [["grand champion remains undefeated.", "asashoryu is tied for the lead with tamanoshima.", "he has won all three of his games this tournament."], 0.04761904761904762], [["grand champion asashoryu remains undefeated.", "he is tied for the lead with tamanoshima.", "he has won all three of his games this tournament."], 0.04597701149425287], [["grand champion asashoryu shows no sign of slowing down.", "he remains undefeated and tied for the lead with tamanoshima."], 0.05333333333333334], [["grand champion asashoryu remains undefeated in spring grand sumo tournament."], 0.24999999999999997], [["grand champions remain undefeated at spring sumo tournament.", "asashoryu beats tosanoumi to remain undefeated."], 0.34074074074074073], [["grand champion asashoryu remains undefeated.", "he is tied for the lead with tamanoshima."], 0.07017543859649122], [["grand champion remains undefeated.", "asashoryu is tied for the lead with tamanoshima."], 0.07407407407407407], [["grand champion asashoryu remains undefeated in spring grand sumo tournament."], 0.24999999999999997], [["grand champion remains undefeated in spring grand sumo tournament."], 0.17777777777777778]], "article_untok": ["grand champion asashoryu showed no sign on letting up friday when he overwhelmed tosanoumi to remain undefeated and tied for the lead with tamanoshima at the spring grand sumo tournament ."], "abstract_untok": ["asashoryu marches on at spring sumo"], "candidates_untok": [[["asashoryu remains undefeated and tied for the lead with tamanoshima at the spring grand sumo tournament."], 0.24242424242424243], [["asashoryu remains undefeated in spring grand sumo tournament.", "grand champion tamanoshima tied for the lead with tamanosima."], 0.17391304347826086], [["grand champion asashoryu remains undefeated in spring grand sumo tournament.", "asashorya is tied for the lead with tamanoshima."], 0.16666666666666666], [["grand champion asashoryu remains undefeated in spring grand sumo tournament.", "asashoryus remains undefeated and tied for the lead with tamanoshima."], 0.15384615384615383], [["grand champion remains undefeated in spring grand sumo tournament.", "asashoryu remains tied for the lead with tamanoshima."], 0.17391304347826086], [["grand sumo champion asashoryu remains undefeated.", "he is tied for the lead with tamanoshima."], 0.10000000000000002], [["asashoryu is still undefeated in the spring grand sumo tournament.", "he is tied with tamanoshima for the lead in the tournament."], 0.14814814814814817], [["grand champion remains undefeated.", "asashoryu is tied for the lead with tamanoshima.", "he has won all three of his games this tournament."], 0.04761904761904762], [["grand champion asashoryu remains undefeated.", "he is tied for the lead with tamanoshima.", "he has won all three of his games this tournament."], 0.04597701149425287], [["grand champion asashoryu shows no sign of slowing down.", "he remains undefeated and tied for the lead with tamanoshima."], 0.05333333333333334], [["grand champion asashoryu remains undefeated in spring grand sumo tournament."], 0.24999999999999997], [["grand champions remain undefeated at spring sumo tournament.", "asashoryu beats tosanoumi to remain undefeated."], 0.34074074074074073], [["grand champion asashoryu remains undefeated.", "he is tied for the lead with tamanoshima."], 0.07017543859649122], [["grand champion remains undefeated.", "asashoryu is tied for the lead with tamanoshima."], 0.07407407407407407], [["grand champion asashoryu remains undefeated in spring grand sumo tournament."], 0.24999999999999997], [["grand champion remains undefeated in spring grand sumo tournament."], 0.17777777777777778]]}