{"article": ["an angry customer opened fire with a shotgun seriously wounding two people at a do-it-yourself hypermarket near here on wednesday ."], "abstract": ["shopper explodes in hypermarket rage"], "candidates": [[["angry customer opened fire with a shotgun seriously wounding two people at a do-it-yourself hypermarket near here."], 0.05555555555555555], [["shooting happened at a do-it-yourself hypermarket near here.", "two people were seriously wounded in the attack."], 0.11594202898550726], [["two people were shot at a do-it-yourself hypermarket near here on wednesday."], 0.07017543859649121], [["two people were shot at a do-it-yourself hypermarket near here.", "the incident happened on wednesday."], 0.0606060606060606], [["two people were shot at a do-it-yourself hypermarket near here."], 0.0784313725490196], [["customer opened fire with a shotgun seriously wounding two people.", "the incident happened at a do-it-yourself hypermarket near here."], 0.05128205128205129], [["shooting happened at a do-it-yourself hypermarket near here."], 0.08888888888888889], [["two people were shot at a do-it-yourself hypermarket near here on wednesday."], 0.07017543859649121], [["an angry customer opened fire with a shotgun seriously wounding two people at a do-it-yourself hypermarket near here."], 0.053333333333333344], [["customer opened fire with a shotgun seriously wounding two people."], 0.0], [["two people were seriously wounded in the shooting.", "the incident occurred in an area known for its diy stores."], 0.05555555555555555], [["customer opens fire with shotgun seriously wounding two people.", "two were shot in the head and one was in the arm."], 0.05128205128205129], [["customer opens fire with shotgun seriously wounding two people."], 0.0], [["angry customer opens fire with a shotgun seriously wounding two people."], 0.0], [["two people were seriously wounded in the shooting."], 0.10256410256410257], [["an angry customer opened fire with a shotgun seriously wounding two people."], 0.0]], "article_untok": ["an angry customer opened fire with a shotgun seriously wounding two people at a do-it-yourself hypermarket near here on wednesday ."], "abstract_untok": ["shopper explodes in hypermarket rage"], "candidates_untok": [[["angry customer opened fire with a shotgun seriously wounding two people at a do-it-yourself hypermarket near here."], 0.05555555555555555], [["shooting happened at a do-it-yourself hypermarket near here.", "two people were seriously wounded in the attack."], 0.11594202898550726], [["two people were shot at a do-it-yourself hypermarket near here on wednesday."], 0.07017543859649121], [["two people were shot at a do-it-yourself hypermarket near here.", "the incident happened on wednesday."], 0.0606060606060606], [["two people were shot at a do-it-yourself hypermarket near here."], 0.0784313725490196], [["customer opened fire with a shotgun seriously wounding two people.", "the incident happened at a do-it-yourself hypermarket near here."], 0.05128205128205129], [["shooting happened at a do-it-yourself hypermarket near here."], 0.08888888888888889], [["two people were shot at a do-it-yourself hypermarket near here on wednesday."], 0.07017543859649121], [["an angry customer opened fire with a shotgun seriously wounding two people at a do-it-yourself hypermarket near here."], 0.053333333333333344], [["customer opened fire with a shotgun seriously wounding two people."], 0.0], [["two people were seriously wounded in the shooting.", "the incident occurred in an area known for its diy stores."], 0.05555555555555555], [["customer opens fire with shotgun seriously wounding two people.", "two were shot in the head and one was in the arm."], 0.05128205128205129], [["customer opens fire with shotgun seriously wounding two people."], 0.0], [["angry customer opens fire with a shotgun seriously wounding two people."], 0.0], [["two people were seriously wounded in the shooting."], 0.10256410256410257], [["an angry customer opened fire with a shotgun seriously wounding two people."], 0.0]]}