{"article": ["president barack obama on thursday made a fresh plea for republicans to back his economic stimulus plan , a day before the huge package is expected to finally clear congress ."], "abstract": ["obama calls on republicans to back stimulus plan"], "candidates": [[["obama makes fresh plea for republicans to back his economic stimulus plan.", "huge package expected to finally clear congress."], 0.3762962962962963], [["president barack obama on th thursday made a fresh plea for republicans to back his economic stimulus plan."], 0.44230769230769235], [["president obama makes a fresh plea for republicans to back his economic stimulus plan."], 0.4636363636363636], [["obama makes fresh plea for republicans to back his economic stimulus plan."], 0.5111111111111111], [["obama urges republicans to back his economic stimulus plan.", "huge package expected to finally clear congress."], 0.42424242424242425], [["obama makes a fresh plea for republicans to back his economic stimulus plan."], 0.4862155388471178], [["a day before the huge package is expected to finally clear congress."], 0.06666666666666667], [["plan expected to pass congress.", "obama makes plea for republicans to back his economic stimulus plan."], 0.42424242424242425], [["obama on thursday made a fresh plea for republicans to back his economic stimulus plan."], 0.5010351966873706], [["barack obama makes fresh plea for republicans to back his economic stimulus plan."], 0.4862155388471178], [["obama urges republicans to back his economic stimulus plan."], 0.603921568627451], [["the president made a fresh plea for republicans to back his economic stimulus plan."], 0.403030303030303], [["obama makes fresh plea for republicans to back his economic stimulus plan."], 0.5111111111111111], [["stimulus plan expected to pass congress."], 0.29365079365079366], [["the president is making a fresh plea for republicans to back his economic stimulus plan."], 0.38509316770186336], [["plan expected to pass congress."], 0.15384615384615385]], "article_untok": ["president barack obama on thursday made a fresh plea for republicans to back his economic stimulus plan , a day before the huge package is expected to finally clear congress ."], "abstract_untok": ["obama calls on republicans to back stimulus plan"], "candidates_untok": [[["obama makes fresh plea for republicans to back his economic stimulus plan.", "huge package expected to finally clear congress."], 0.3762962962962963], [["president barack obama on th thursday made a fresh plea for republicans to back his economic stimulus plan."], 0.44230769230769235], [["president obama makes a fresh plea for republicans to back his economic stimulus plan."], 0.4636363636363636], [["obama makes fresh plea for republicans to back his economic stimulus plan."], 0.5111111111111111], [["obama urges republicans to back his economic stimulus plan.", "huge package expected to finally clear congress."], 0.42424242424242425], [["obama makes a fresh plea for republicans to back his economic stimulus plan."], 0.4862155388471178], [["a day before the huge package is expected to finally clear congress."], 0.06666666666666667], [["plan expected to pass congress.", "obama makes plea for republicans to back his economic stimulus plan."], 0.42424242424242425], [["obama on thursday made a fresh plea for republicans to back his economic stimulus plan."], 0.5010351966873706], [["barack obama makes fresh plea for republicans to back his economic stimulus plan."], 0.4862155388471178], [["obama urges republicans to back his economic stimulus plan."], 0.603921568627451], [["the president made a fresh plea for republicans to back his economic stimulus plan."], 0.403030303030303], [["obama makes fresh plea for republicans to back his economic stimulus plan."], 0.5111111111111111], [["stimulus plan expected to pass congress."], 0.29365079365079366], [["the president is making a fresh plea for republicans to back his economic stimulus plan."], 0.38509316770186336], [["plan expected to pass congress."], 0.15384615384615385]]}