{"article": ["moving this from a separate thread to a comment)   ( this was posted by  )   the sci-fidelity podcast talks about all the coolest shit we're watching on tv, comics and in the movies.", "i am one of the 4 co-hosts - steve.", "we just published f"], "abstract": ["ag racing - a compairative breakdown of faster than light ships in science fiction.", "check it out:  (that's sci fi ftl, all lowercase)"], "candidates": [[["the sci-fidelity podcast talks about all the coolest shit we're watching on tv, comics and in the movies."], 0.09302325581395349], [["the sci-fidelity podcast talks about all the coolest shit we're watching on tv, comics and in the movies."], 0.09302325581395349], [["the sci-fidelity podcast talks about all the coolest shit we're watching on tv, comics and in the movies."], 0.09302325581395349], [["sci-fidelity is a podcast that talks about all the coolest shit we're watching on tv, comics and in the movies."], 0.13333333333333333], [["moving this from a separate thread to a comment."], 0.041666666666666664], [["sci-fidelity podcast talks about all the coolest shit we're watching on tv, comics and in the movies.", "we just published f."], 0.08695652173913043], [["sci-fidelity podcast talks about all the coolest shit we're watching on tv, comics and in the movies."], 0.09523809523809525], [["sci-fidelity podcast talks about all the coolest shit we're watching on tv, comics and in the movies."], 0.09523809523809525], [["sci-friy podcast is a weekly look at what's happening in the world of comics, tv, and movies."], 0.12698412698412698], [["move from a separate thread to a comment."], 0.04301075268817204], [["the sci-f fidelity podcast is on itunes and stitcher.", "the podcast is hosted by steve.", "we just published f-1."], 0.0303030303030303], [["the sci-fidelity podcast talks about all the coolest shit we're watching on tv, comics and in the movies."], 0.09302325581395349], [["the sci-f fidelity podcast is on itunes and stitcher.", "the podcast is hosted by steve."], 0.034188034188034185], [["the sci-fidelity podcast is one of four shows on the sci-fi channel."], 0.12715572715572712], [["moving this from a separate thread to a comment."], 0.041666666666666664], [["the sci-f fidelity podcast is on itunes and stitcher."], 0.04040404040404041]], "article_untok": ["moving this from a separate thread to a comment)   ( this was posted by  )   the sci-fidelity podcast talks about all the coolest shit we're watching on tv, comics and in the movies.", "i am one of the 4 co-hosts - steve.", "we just published f"], "abstract_untok": ["ag racing - a compairative breakdown of faster than light ships in science fiction.", "check it out:  (that's sci fi ftl, all lowercase)"], "candidates_untok": [[["the sci-fidelity podcast talks about all the coolest shit we're watching on tv, comics and in the movies."], 0.09302325581395349], [["the sci-fidelity podcast talks about all the coolest shit we're watching on tv, comics and in the movies."], 0.09302325581395349], [["the sci-fidelity podcast talks about all the coolest shit we're watching on tv, comics and in the movies."], 0.09302325581395349], [["sci-fidelity is a podcast that talks about all the coolest shit we're watching on tv, comics and in the movies."], 0.13333333333333333], [["moving this from a separate thread to a comment."], 0.041666666666666664], [["sci-fidelity podcast talks about all the coolest shit we're watching on tv, comics and in the movies.", "we just published f."], 0.08695652173913043], [["sci-fidelity podcast talks about all the coolest shit we're watching on tv, comics and in the movies."], 0.09523809523809525], [["sci-fidelity podcast talks about all the coolest shit we're watching on tv, comics and in the movies."], 0.09523809523809525], [["sci-friy podcast is a weekly look at what's happening in the world of comics, tv, and movies."], 0.12698412698412698], [["move from a separate thread to a comment."], 0.04301075268817204], [["the sci-f fidelity podcast is on itunes and stitcher.", "the podcast is hosted by steve.", "we just published f-1."], 0.0303030303030303], [["the sci-fidelity podcast talks about all the coolest shit we're watching on tv, comics and in the movies."], 0.09302325581395349], [["the sci-f fidelity podcast is on itunes and stitcher.", "the podcast is hosted by steve."], 0.034188034188034185], [["the sci-fidelity podcast is one of four shows on the sci-fi channel."], 0.12715572715572712], [["moving this from a separate thread to a comment."], 0.041666666666666664], [["the sci-f fidelity podcast is on itunes and stitcher."], 0.04040404040404041]]}