{"article": ["i guess they still haven't mowed it, eh?", ":-/   we played there 2 saturdays ago and 3 of us drove @ 26 and all 3 of us lost our frikin discs.", "we looked for a good 30 minutes and couldn't find a damn thing in that tall grass over there.", "it really sucks because my friend threw his first ace disc on #24 and lost it, then his other ace disc on #26 and lost that one.", "all of our discs had our names/numbers on them but nobody has called.", "epic sadface."], "abstract": ["don't play the back 9 again at ryan ranch until they mow it"], "candidates": [[["three friends drove to the park to play and lost their discs.", "they looked for 30 minutes and couldn't find them.", "all three discs had their names and numbers on them.", "it's sad."], 0.108843537414966], [["three friends drove to the park to play and lost their discs.", "they looked for 30 minutes and couldn't find them.", "all three discs had their names and numbers on them."], 0.08695652173913043], [["the club has not mowed its grass in two weeks.", "the club has lost three of its discs.", "the discs had our names/numbers on them but nobody has called."], 0.06060606060606061], [["the team lost all three of their discs.", "they were thrown on 26. the grass is still tall.", "it's sad.", "they haven't called.", "it really sucks.", "it was a great game."], 0.09929078014184396], [["a friend and two others lost their discs at the park.", "they were thrown on the same day.", "the park is still not mowed.", "it's sad.", "they should have called."], 0.14883720930232558], [["the team lost all three of their discs.", "they were thrown on 26. the grass is still tall.", "it's sad.", "they haven't called.", "it really sucks."], 0.1111111111111111], [["a friend and two others lost their discs at the park.", "they were thrown on the same day.", "the park is still not mowed.", "it's sad."], 0.14717531790702523], [["three friends drove to the park to play and lost their discs.", "they looked for 30 minutes and couldn't find them."], 0.1111111111111111], [["the team lost all three of their discs.", "they were thrown on 26. the grass is still tall.", "it's sad.", "they haven't called."], 0.11965811965811964], [["a friend and two others lost their discs at the park.", "they were thrown on the same day.", "the park is still not mowed."], 0.10526315789473685], [["three players lost their discs at the park.", "all three have not called to claim them.", "the park is still in the middle of a field."], 0.05000000000000001], [["the team lost all three of their discs.", "they were thrown on 26. the grass is still tall.", "it's sad."], 0.09523809523809523], [["the team lost all three of their discs.", "they were thrown on 26. the grass is still tall."], 0.0625], [["the club has not mowed its grass in two weeks.", "the club has lost three of its discs."], 0.08333333333333333], [["three players lost their discs at the park.", "all three have not called to claim them."], 0.06666666666666667], [["the club has not mowed its grass in two weeks."], 0.1111111111111111]], "article_untok": ["i guess they still haven't mowed it, eh?", ":-/   we played there 2 saturdays ago and 3 of us drove @ 26 and all 3 of us lost our frikin discs.", "we looked for a good 30 minutes and couldn't find a damn thing in that tall grass over there.", "it really sucks because my friend threw his first ace disc on #24 and lost it, then his other ace disc on #26 and lost that one.", "all of our discs had our names/numbers on them but nobody has called.", "epic sadface."], "abstract_untok": ["don't play the back 9 again at ryan ranch until they mow it"], "candidates_untok": [[["three friends drove to the park to play and lost their discs.", "they looked for 30 minutes and couldn't find them.", "all three discs had their names and numbers on them.", "it's sad."], 0.108843537414966], [["three friends drove to the park to play and lost their discs.", "they looked for 30 minutes and couldn't find them.", "all three discs had their names and numbers on them."], 0.08695652173913043], [["the club has not mowed its grass in two weeks.", "the club has lost three of its discs.", "the discs had our names/numbers on them but nobody has called."], 0.06060606060606061], [["the team lost all three of their discs.", "they were thrown on 26. the grass is still tall.", "it's sad.", "they haven't called.", "it really sucks.", "it was a great game."], 0.09929078014184396], [["a friend and two others lost their discs at the park.", "they were thrown on the same day.", "the park is still not mowed.", "it's sad.", "they should have called."], 0.14883720930232558], [["the team lost all three of their discs.", "they were thrown on 26. the grass is still tall.", "it's sad.", "they haven't called.", "it really sucks."], 0.1111111111111111], [["a friend and two others lost their discs at the park.", "they were thrown on the same day.", "the park is still not mowed.", "it's sad."], 0.14717531790702523], [["three friends drove to the park to play and lost their discs.", "they looked for 30 minutes and couldn't find them."], 0.1111111111111111], [["the team lost all three of their discs.", "they were thrown on 26. the grass is still tall.", "it's sad.", "they haven't called."], 0.11965811965811964], [["a friend and two others lost their discs at the park.", "they were thrown on the same day.", "the park is still not mowed."], 0.10526315789473685], [["three players lost their discs at the park.", "all three have not called to claim them.", "the park is still in the middle of a field."], 0.05000000000000001], [["the team lost all three of their discs.", "they were thrown on 26. the grass is still tall.", "it's sad."], 0.09523809523809523], [["the team lost all three of their discs.", "they were thrown on 26. the grass is still tall."], 0.0625], [["the club has not mowed its grass in two weeks.", "the club has lost three of its discs."], 0.08333333333333333], [["three players lost their discs at the park.", "all three have not called to claim them."], 0.06666666666666667], [["the club has not mowed its grass in two weeks."], 0.1111111111111111]]}